[
  {
    "snapshot": 1,
    "mutatorCount": "0",
    "statusCount": 8120,
    "cachedCount": 2,
    "cachedFiles": [
      "M\tassets/css/global.css",
      "M\tassets/css/global.min.css"
    ],
    "nameStatusCount": null,
    "nameOnlyCount": null
  },
  {
    "snapshot": 2,
    "mutatorCount": "0",
    "statusCount": 8120,
    "cachedCount": 2,
    "cachedFiles": [
      "M\tassets/css/global.css",
      "M\tassets/css/global.min.css"
    ],
    "nameStatusCount": null,
    "nameOnlyCount": null
  },
  {
    "snapshot": 3,
    "mutatorCount": "0",
    "statusCount": 8120,
    "cachedCount": 2,
    "cachedFiles": [
      "M\tassets/css/global.css",
      "M\tassets/css/global.min.css"
    ],
    "nameStatusCount": null,
    "nameOnlyCount": null
  }
]