{
  "schemaVersion": 1,
  "toolKey": "paystack-calculator",
  "legacyTextSha256": "sha256:e3b0c44298fc1c149afbf4c8996fb92427ae41e4649b934ca495991b7852b855",
  "status": "source-coupled",
  "staticText": "Route-only Paystack merchant fee planner in native English, French and Hausa. The browser-local engine supports only the reviewed merchant-country and payment-channel combinations that its readable engine owns, locks currency to merchant country, and hard-blocks after its engine-owned review deadline. It never treats a fixed-fee waiver as a whole-fee waiver and infers fee tax only where the official pricing explicitly states that rates exclude tax. Monthly and target-net outputs are deterministic planning, not forecasts or quotes. Payout transfer fees, transfer duties, refunds, chargebacks, foreign exchange, custom or school pricing, terminal pricing, disputes and settlement timing are excluded. No widget, fee API, prefill, live quote or Paystack affiliation is supplied.",
  "sourceBindings": [
    {
      "kind": "paystack-fee-planner",
      "toolId": "paystack-calculator",
      "route": "/tools/paystack-calculator/",
      "artifactPath": "tools/paystack-calculator/index.html",
      "enginePath": "assets/js/engines/paystack-fee-planner.js"
    }
  ]
}
